gbase8s_sqlalchemy/__init__.py
gbase8s_sqlalchemy/base.py
gbase8s_sqlalchemy/gbase8sdb.py
gbase8s_sqlalchemy/provision.py
gbase8s_sqlalchemy/requirements.py
gbase8s_sqlalchemy/types.py
gbase8s_sqlalchemy-2.0.1.dist-info/LICENSE
gbase8s_sqlalchemy-2.0.1.dist-info/METADATA
gbase8s_sqlalchemy-2.0.1.dist-info/WHEEL
gbase8s_sqlalchemy-2.0.1.dist-info/entry_points.txt
gbase8s_sqlalchemy-2.0.1.dist-info/top_level.txt
gbase8s_sqlalchemy-2.0.1.dist-info/RECORD
