Metadata-Version: 2.1
Name: gbase8s-sqlalchemy
Version: 2.0.1
Summary: GBase 8s Dialect for SQLAlchemy
Home-page: https://gitee.com/GBase8s/sqlalchemy-gbase8s
Author: GBase 8s team
License: MIT
Keywords: GBase 8s,database,sqlalchemy
Platform: UNKNOWN
Requires-Python: >=3.8
License-File: LICENSE
Requires-Dist: sqlalchemy~=2.0.0
Requires-Dist: gbase8sdb
